boost_loss/__init__.py
boost_loss/base.py
boost_loss/debug.py
boost_loss/py.typed
boost_loss/regression/__init__.py
boost_loss/regression/asymmetric.py
boost_loss/regression/regression.py
boost_loss/regression/sklearn.py
boost_loss/resuming.py
boost_loss/sklearn.py
boost_loss/torch.py
boost_loss-0.5.5.dist-info/LICENSE
boost_loss-0.5.5.dist-info/METADATA
boost_loss-0.5.5.dist-info/WHEEL
boost_loss-0.5.5.dist-info/RECORD
