Metadata-Version: 2.1
Name: boost-loss
Version: 0.5.5
Summary: Utilities for easy use of custom losses in CatBoost, LightGBM, XGBoost
Home-page: https://github.com/34j/boost-loss
License: MIT
Author: 34j
Author-email: 34j.95a2p@simplelogin.com
Requires-Python: >=3.8,<4.0
Classifier: Development Status :: 2 - Pre-Alpha
Classifier: Intended Audience :: Developers
Classifier: License :: OSI Approved :: MIT License
Classifier: Natural Language :: English
Classifier: Operating System :: OS Independent
Classifier: Programming Language :: Python :: 3
Classifier: Programming Language :: Python :: 3.8
Classifier: Programming Language :: Python :: 3.9
Classifier: Programming Language :: Python :: 3.10
Classifier: Programming Language :: Python :: 3.11
Classifier: Programming Language :: Python :: 3.12
Classifier: Topic :: Software Development :: Libraries
Requires-Dist: attrs (>=23.1.0,<24.0.0)
Requires-Dist: catboost (>=1.2,<2.0)
Requires-Dist: lightgbm (>=4.0.0,<5.0.0)
Requires-Dist: pyhumps (>=3.8.0,<4.0.0)
Requires-Dist: scikit-learn (>=1.3.2,<2.0.0)
Requires-Dist: xgboost (>=2.0.0,<3.0.0)
Project-URL: Bug Tracker, https://github.com/34j/boost-loss/issues
Project-URL: Changelog, https://github.com/34j/boost-loss/blob/main/CHANGELOG.md
Project-URL: Documentation, https://boost-loss.readthedocs.io
Project-URL: Repository, https://github.com/34j/boost-loss
